multirpc/__init__.py
multirpc/async_multi_rpc_interface.py
multirpc/base_multi_rpc_interface.py
multirpc/constants.py
multirpc/exceptions.py
multirpc/gas_estimation.py
multirpc/sync_multi_rpc_interface.py
multirpc/tx_trace.py
multirpc/utils.py
solver_multirpc-3.1.11.dist-info/METADATA
solver_multirpc-3.1.11.dist-info/WHEEL
solver_multirpc-3.1.11.dist-info/RECORD
