Metadata-Version: 2.3
Name: solver-multirpc
Version: 3.1.11
Summary: A robust Python library for interacting with Ethereum smart contracts via multiple RPC endpoints, ensuring reliability, availability, and load distribution with automatic retries on failure.
License: MIT
Author: rorschach
Author-email: rorschach45001@gmail.com
Requires-Python: >=3.10,<4.0
Classifier: License :: OSI Approved :: MIT License
Classifier: Programming Language :: Python :: 3
Classifier: Programming Language :: Python :: 3.10
Classifier: Programming Language :: Python :: 3.11
Classifier: Programming Language :: Python :: 3.12
Classifier: Programming Language :: Python :: 3.13
Requires-Dist: eth-account (>=0.13.0)
Requires-Dist: multicallable (>=6.0.0)
Requires-Dist: web3 (>7.0.0)
